genemunge/__init__.py
genemunge/convert.py
genemunge/describe.py
genemunge/normalize.py
genemunge/search.py
genemunge/data/__init__.py
genemunge/data/cleanup.py
genemunge/data/downloads.py
genemunge/data/gene_attributes.json
genemunge/data/gene_attributes.py
genemunge/data/go.json
genemunge/data/hgnc_complete_set.txt
genemunge/data/parse_go.py
genemunge/data/gtex/__init__.py
genemunge/data/gtex/gene_info.csv
genemunge/data/gtex/process_gtex.py
genemunge/data/gtex/tissue_stats.h5
genemunge-0.0.dist-info/DESCRIPTION.rst
genemunge-0.0.dist-info/LICENSE.txt
genemunge-0.0.dist-info/METADATA
genemunge-0.0.dist-info/RECORD
genemunge-0.0.dist-info/WHEEL
genemunge-0.0.dist-info/metadata.json
genemunge-0.0.dist-info/top_level.txt
