Metadata-Version: 2.0
Name: genemunge
Version: 0.0
Summary: Tools for munging genomics data
Home-page: http://github.com/unlearnai/genemunge
Author: Unlearn.AI, Inc.
Author-email: drckf@unlearn.ai
License: MIT
Keywords: bioinformatics genomics
Platform: UNKNOWN
Classifier: Development Status :: 4 - Beta
Classifier: Intended Audience :: Science/Research
Classifier: Topic :: Scientific/Engineering :: Bio-Informatics
Classifier: License :: OSI Approved :: MIT License
Classifier: Programming Language :: Python :: 3.5
Classifier: Programming Language :: Python :: 3.6
Requires-Python: >=3.5
Requires-Dist: h5py
Requires-Dist: matplotlib
Requires-Dist: numpy
Requires-Dist: pandas
Requires-Dist: pytest
Requires-Dist: seaborn
Requires-Dist: tables
Requires-Dist: cytoolz
